README.md
setup.py
universal_date_parser/__init__.py
universal_date_parser/parser.py
universal_date_parser.egg-info/PKG-INFO
universal_date_parser.egg-info/SOURCES.txt
universal_date_parser.egg-info/dependency_links.txt
universal_date_parser.egg-info/top_level.txt