Metadata-Version: 2.1
Name: universal-date-parser
Version: 0.0.2.1
Summary: A universal date parser to parse any kind of (possible) date strings.
Home-page: https://github.com/guangyu-he/universal_date_parser
Author: Guangyu He
Author-email: me@heguangyu.net
Classifier: Development Status :: 3 - Alpha
Classifier: Programming Language :: Python :: 3
Classifier: Operating System :: OS Independent
Requires-Python: >=3.7
